another_ayx_python_sdk/__init__.py
another_ayx_python_sdk/__main__.py
another_ayx_python_sdk/version.py
another_ayx_python_sdk/assets/base_tool_config/Config.xml
another_ayx_python_sdk/assets/base_tool_config/icon.png
another_ayx_python_sdk/assets/executables/yxi-installer.pyz
another_ayx_python_sdk/assets/workspace_files/__init__.py
another_ayx_python_sdk/assets/workspace_files/requirements-local.txt
another_ayx_python_sdk/assets/workspace_files/requirements-thirdparty.txt
another_ayx_python_sdk/assets/workspace_files/setup.py
another_ayx_python_sdk/assets/workspace_files/__pycache__/__init__.cpython-310.pyc
another_ayx_python_sdk/assets/workspace_files/__pycache__/setup.cpython-310.pyc
another_ayx_python_sdk/cli/__init__.py
another_ayx_python_sdk/cli/utilities.py
another_ayx_python_sdk/cli/workspace.py
another_ayx_python_sdk/cli/yxi_builder.py
another_ayx_python_sdk/cli/yxi_installer.py
another_ayx_python_sdk/core/__init__.py
another_ayx_python_sdk/core/constants.py
another_ayx_python_sdk/core/dcm_base.py
another_ayx_python_sdk/core/doc_utilities.py
another_ayx_python_sdk/core/environment_base.py
another_ayx_python_sdk/core/exceptions.py
another_ayx_python_sdk/core/field.py
another_ayx_python_sdk/core/input_anchor_base.py
another_ayx_python_sdk/core/input_connection_base.py
another_ayx_python_sdk/core/io_base.py
another_ayx_python_sdk/core/metadata.py
another_ayx_python_sdk/core/observable_mixin.py
another_ayx_python_sdk/core/output_anchor_base.py
another_ayx_python_sdk/core/plugin.py
another_ayx_python_sdk/core/plugin_v2.py
another_ayx_python_sdk/core/provider_base.py
another_ayx_python_sdk/core/proxy_requests.py
another_ayx_python_sdk/core/record_packet.py
another_ayx_python_sdk/core/record_packet_base.py
another_ayx_python_sdk/core/register_plugin.py
another_ayx_python_sdk/core/testing.py
another_ayx_python_sdk/core/utils.py
another_ayx_python_sdk/core/__pycache__/__init__.cpython-310.pyc
another_ayx_python_sdk/core/__pycache__/constants.cpython-310.pyc
another_ayx_python_sdk-2.5.4.dist-info/licenses/LICENSE
another_ayx_python_sdk-2.5.4.dist-info/METADATA
another_ayx_python_sdk-2.5.4.dist-info/WHEEL
another_ayx_python_sdk-2.5.4.dist-info/entry_points.txt
another_ayx_python_sdk-2.5.4.dist-info/top_level.txt
another_ayx_python_sdk-2.5.4.dist-info/RECORD
