Metadata-Version: 2.4
Name: another-ayx-python-sdk
Version: 2.5.4
Summary: Python SDK for Alteryx Plugin Development and Testing
Author: Jupiter Bakakeu
Author-email: Jupiter Bakakeu <jupiter.bakakeu@gmail.com>
Maintainer: Jupiter Bakakeu
Maintainer-email: Jupiter Bakakeu <jupiter.bakakeu@gmail.com>
License-Expression: MIT
Project-URL: Homepage, https://github.com/jupiterbak/another-ayx-python-sdk
Project-URL: Repository, https://github.com/jupiterbak/another-ayx-python-sdk.git
Classifier: Development Status :: 5 - Production/Stable
Classifier: Intended Audience :: Developers
Classifier: Programming Language :: Python :: 3
Classifier: Programming Language :: Python :: 3.8
Classifier: Programming Language :: Python :: 3.9
Classifier: Programming Language :: Python :: 3.10
Classifier: Programming Language :: Python :: 3.11
Classifier: Programming Language :: Python :: 3.12
Classifier: Topic :: Software Development :: Libraries :: Python Modules
Classifier: Topic :: Software Development :: Build Tools
Classifier: Topic :: Software Development :: Testing
Classifier: Environment :: Console
Requires-Python: >=3.8
License-File: LICENSE
Requires-Dist: pydantic
Requires-Dist: packaging
Requires-Dist: setuptools>=65.5.0
Requires-Dist: pyarrow
Requires-Dist: xmltodict
Requires-Dist: pyyaml
Requires-Dist: requests
Requires-Dist: another-ayx-plugin-cli>=1.2.4
Requires-Dist: typing-extensions
Requires-Dist: pypac
Requires-Dist: pandas
Requires-Dist: numpy
Requires-Dist: deprecation
Requires-Dist: grpcio
Requires-Dist: grpcio-tools
Requires-Dist: protobuf
Requires-Dist: psutil
Requires-Dist: Click
Requires-Dist: python-dateutil
Requires-Dist: pytz
Requires-Dist: six
Requires-Dist: typer
Requires-Dist: wincertstore
Provides-Extra: dev
Requires-Dist: pytest; extra == "dev"
Requires-Dist: pytest-cov; extra == "dev"
Requires-Dist: black; extra == "dev"
Requires-Dist: isort; extra == "dev"
Requires-Dist: flake8; extra == "dev"
Requires-Dist: mypy; extra == "dev"
Requires-Dist: twine; extra == "dev"
Dynamic: author
Dynamic: license-file
Dynamic: maintainer
Dynamic: requires-python
